lotr_sdk/__init__.py
lotr_sdk/sdk.py
tests/__init__.py
tests/test_sdk.py
the_one_lotr_sdk-0.1.0.dist-info/METADATA
the_one_lotr_sdk-0.1.0.dist-info/WHEEL
the_one_lotr_sdk-0.1.0.dist-info/top_level.txt
the_one_lotr_sdk-0.1.0.dist-info/RECORD
