Metadata-Version: 2.1
Name: the-one-lotr-sdk
Version: 0.1.0
Summary: SDK for The Lord of the Rings API
Home-page: https://github.com/andrewpos/lotr_sdk
Author: Andrew Pos
Author-email: andrewmpos@gmail.com
License: UNKNOWN
Platform: UNKNOWN
Requires-Dist: requests (==2.25.1)
